odoo/addons/barcodes_generator_product_multi_barcode/README.rst
odoo/addons/barcodes_generator_product_multi_barcode/__init__.py
odoo/addons/barcodes_generator_product_multi_barcode/__manifest__.py
odoo/addons/barcodes_generator_product_multi_barcode/i18n/barcodes_generator_product_multi_barcode.pot
odoo/addons/barcodes_generator_product_multi_barcode/i18n/it.po
odoo/addons/barcodes_generator_product_multi_barcode/models/__init__.py
odoo/addons/barcodes_generator_product_multi_barcode/models/product_product.py
odoo/addons/barcodes_generator_product_multi_barcode/readme/CONFIGURE.rst
odoo/addons/barcodes_generator_product_multi_barcode/readme/CONTRIBUTORS.rst
odoo/addons/barcodes_generator_product_multi_barcode/readme/DESCRIPTION.rst
odoo/addons/barcodes_generator_product_multi_barcode/readme/USAGE.rst
odoo/addons/barcodes_generator_product_multi_barcode/static/description/icon.png
odoo/addons/barcodes_generator_product_multi_barcode/static/description/index.html
odoo/addons/barcodes_generator_product_multi_barcode/tests/__init__.py
odoo/addons/barcodes_generator_product_multi_barcode/tests/test_multi_barcodes_generator_product.py
odoo14_addon_barcodes_generator_product_multi_barcode-14.0.1.0.2.dist-info/METADATA
odoo14_addon_barcodes_generator_product_multi_barcode-14.0.1.0.2.dist-info/WHEEL
odoo14_addon_barcodes_generator_product_multi_barcode-14.0.1.0.2.dist-info/top_level.txt
odoo14_addon_barcodes_generator_product_multi_barcode-14.0.1.0.2.dist-info/RECORD
