Metadata-Version: 2.1
Name: odoo14-addon-barcodes-generator-product-multi-barcode
Version: 14.0.1.0.2
Summary: Barcode Generator product - multi barcode
Home-page: https://github.com/OCA/stock-logistics-barcode
Author: Ooops, Cetmix, La Louve, Odoo Community Association (OCA)
Author-email: support@odoo-community.org
License: AGPL-3
Platform: UNKNOWN
Classifier: Programming Language :: Python
Classifier: Framework :: Odoo
Classifier: Framework :: Odoo :: 14.0
Classifier: License :: OSI Approved :: GNU Affero General Public License v3
Requires-Python: >=3.6
Requires-Dist: odoo14-addon-barcodes-generator-abstract
Requires-Dist: odoo14-addon-barcodes-generator-location
Requires-Dist: odoo14-addon-barcodes-generator-product
Requires-Dist: odoo14-addon-product-multi-barcode
Requires-Dist: odoo <14.1dev,>=14.0a
